LICENCE
setup.py
Flask_ClickUz.egg-info/PKG-INFO
Flask_ClickUz.egg-info/SOURCES.txt
Flask_ClickUz.egg-info/dependency_links.txt
Flask_ClickUz.egg-info/not-zip-safe
Flask_ClickUz.egg-info/requires.txt
Flask_ClickUz.egg-info/top_level.txt
flask_clickuz/__init__.py
flask_clickuz/blueprint.py
flask_clickuz/errors.py
flask_clickuz/exceptions.py